rithlog/__init__.py
rithlog-0.0.1.dist-info/METADATA
rithlog-0.0.1.dist-info/WHEEL
rithlog-0.0.1.dist-info/top_level.txt
rithlog-0.0.1.dist-info/RECORD
